{
  "status": "awaiting_photo_confirm",
  "content_type": "worldcup",
  "story": {
    "title": "2026 북중미 월드컵 음바페-홀란드-메시, 첫 경기서 나란히 멀티골",
    "link": "https://news.google.com/rss/articles/CBMickFVX3lxTE9JRzB0cEF1Y3BXWnM3SFFRUDVhVWR2MkpyM083c2FRQXhJRFJyTS1HM3FfM3l5ZVNqb0xoczNoYml5U1RocnhDc1liUTJiNHpGaEZYNlZqNUh4d3h3cjVTVnJqMTBqUkQ4ODFKWk51UTRnUQ?oc=5",
    "published": "Wed, 17 Jun 2026 03:25:46 GMT",
    "title_ko": "2026 북중미 월드컵 음바페-홀란드-메시, 첫 경기서 나란히 멀티골",
    "lang": "ko",
    "priority": 3,
    "short_link": "https://tinyurl.com/2cc4xbme"
  },
  "extracted_data": {
    "team_a": "TEAM A",
    "team_b": "TEAM B",
    "score_a": "?",
    "score_b": "?",
    "eyebrow": "WC '26 · Wed, 17 Ju",
    "headline_line1": "2026 북중미 월드컵 음바페-홀란드-메시",
    "headline_line2": "첫 경기서 나란히",
    "point_01": "TEAM A 승리 · ?-?",
    "point_02": "주요 장면 하이라이트",
    "point_03": "경기 총평",
    "view01_title": "경기 흐름",
    "view01_text": "2026 북중미 월드컵 음바페-홀란드-메시, 첫 경기서 나란히 멀티골",
    "view02_title": "핵심 포인트",
    "view02_text": "TEAM A와 TEAM B의 다음 경기가 주목된다.",
    "next_label": "NEXT MATCH",
    "match_a_date": "TBD",
    "match_a_home": "TEAM A",
    "match_a_away": "TBD",
    "match_a_venue": "Stadium TBD",
    "match_b_date": "TBD",
    "match_b_home": "TEAM B",
    "match_b_away": "TBD",
    "match_b_venue": "Stadium TBD",
    "team_a_class": "tea",
    "team_b_class": "tea"
  },
  "photos": {
    "s1": "https://upload.wikimedia.org/wikipedia/commons/9/9b/Aerial_view_of_Arrowhead_Stadium_08-31-2013_crop.jpg",
    "s2": "https://shop-phinf.pstatic.net/20260526_203/1779795962855sx00Y_JPEG/72521081150525959_1240928877.jpeg",
    "s3": "https://i.ytimg.com/vi/71w_dI4Gk9s/maxresdefault.jpg"
  },
  "tried_urls": [
    "https://upload.wikimedia.org/wikipedia/commons/9/9b/Aerial_view_of_Arrowhead_Stadium_08-31-2013_crop.jpg",
    "https://shop-phinf.pstatic.net/20260526_203/1779795962855sx00Y_JPEG/72521081150525959_1240928877.jpeg",
    "https://i.ytimg.com/vi/71w_dI4Gk9s/maxresdefault.jpg"
  ],
  "last_message_id": "1517181284370219110"
}